AUTHORS
ChangeLog
MANIFEST.in
README.rst
requirements.txt
setup.cfg
setup.py
leonardo_module_vis_relational/__init__.py
leonardo_module_vis_relational/admin.py
leonardo_module_vis_relational/models.py
leonardo_module_vis_relational/urls.py
leonardo_module_vis_relational.egg-info/PKG-INFO
leonardo_module_vis_relational.egg-info/SOURCES.txt
leonardo_module_vis_relational.egg-info/dependency_links.txt
leonardo_module_vis_relational.egg-info/not-zip-safe
leonardo_module_vis_relational.egg-info/pbr.json
leonardo_module_vis_relational.egg-info/requires.txt
leonardo_module_vis_relational.egg-info/top_level.txt
leonardo_module_vis_relational/migrations/0001_initial.py
leonardo_module_vis_relational/migrations/__init__.py
leonardo_module_vis_relational/static/vendor/css/cal-heatmap.css
leonardo_module_vis_relational/static/vendor/js/cal-heatmap.js
leonardo_module_vis_relational/static/vendor/js/d3.cola.js
leonardo_module_vis_relational/static/vendor/js/d3.dagre.js
leonardo_module_vis_relational/static/vendor/js/d3.layout.orbit.js
leonardo_module_vis_relational/static/vendor/js/d3.layout.voronoitreemap.js
leonardo_module_vis_relational/static/vendor/js/d3.tip.js
leonardo_module_vis_relational/static/vis/js/adjacencymatrix.js
leonardo_module_vis_relational/static/vis/js/arcdiagram.js
leonardo_module_vis_relational/static/vis/js/bubblechart.js
leonardo_module_vis_relational/static/vis/js/circlepacking.js
leonardo_module_vis_relational/static/vis/js/dendrogramlinear.js
leonardo_module_vis_relational/static/vis/js/dendrogramradial.js
leonardo_module_vis_relational/static/vis/js/edgebundle.js
leonardo_module_vis_relational/static/vis/js/edgetreemap.js
leonardo_module_vis_relational/static/vis/js/forcedirectedgraph.js
leonardo_module_vis_relational/static/vis/js/hiveplot.js
leonardo_module_vis_relational/static/vis/js/icicle.js
leonardo_module_vis_relational/static/vis/js/indentedtree.js
leonardo_module_vis_relational/static/vis/js/orbit.js
leonardo_module_vis_relational/static/vis/js/reingoldtilfordtreelinear.js
leonardo_module_vis_relational/static/vis/js/reingoldtilfordtreeradial.js
leonardo_module_vis_relational/static/vis/js/sunburst.js
leonardo_module_vis_relational/static/vis/js/treemap.js
leonardo_module_vis_relational/static/vis/js/voronoitreemap.js
leonardo_module_vis_relational/static/vis/json/flare.json
